pytrumpet/__init__.py
pytrumpet-0.1.0.dist-info/WHEEL
pytrumpet-0.1.0.dist-info/METADATA
pytrumpet-0.1.0.dist-info/RECORD
