Metadata-Version: 2.1
Name: pytrumpet
Version: 0.1.0
Summary: 
Author: Joseph Chu
Author-email: josephchu21@gmail.com
Requires-Python: >=3.10,<4.0
Classifier: Programming Language :: Python :: 3
Classifier: Programming Language :: Python :: 3.10
Requires-Dist: pybind11 (>=2.10.0,<3.0.0)
